ros2_test_runner/__init__.py
ros2_test_runner/runner.py
ros2_test_runner/util.py
ros2_test_runner-0.0.2.dist-info/METADATA
ros2_test_runner-0.0.2.dist-info/WHEEL
ros2_test_runner-0.0.2.dist-info/top_level.txt
ros2_test_runner-0.0.2.dist-info/RECORD
