Metadata-Version: 2.1
Name: ros2-test-runner
Version: 0.0.2
Summary: A python package to conveniently collect statistics data in ros2
Home-page: UNKNOWN
Author: Tharaka Sachintha 
Author-email: <tharakasachintha27@gmail.com>
License: UNKNOWN
Keywords: python,ros2,humble,launch
Platform: UNKNOWN
Classifier: Development Status :: 1 - Planning
Classifier: Intended Audience :: Developers
Classifier: Programming Language :: Python :: 3
Classifier: Operating System :: Unix
Classifier: Operating System :: MacOS :: MacOS X
Classifier: Operating System :: Microsoft :: Windows
